benchmarks/__init__.py
benchmarks/benchmark_func.py
docs/README.md
docs/__init__.py
docs/source/__init__.py
docs/source/conf.py
notus/README.md
notus/__init__.py
notus/backend_selection.py
notus/notification.py
notus/builtin_plugins/__init__.py
notus/builtin_plugins/discord/__init__.py
notus/builtin_plugins/discord/bot.py
notus/builtin_plugins/discord/client.py
notus/builtin_plugins/email/__init__.py
notus/builtin_plugins/gpio/__init__.py
notus/builtin_plugins/keybase/__init__.py
notus/builtin_plugins/slack/__init__.py
notus/builtin_plugins/sound/__init__.py
notus/entry_points/__init__.py
notus/entry_points/toast.py
notus/gtk_dbus/__init__.py
notus/gtk_dbus/gtk_toaster.py
notus/osx/__init__.py
notus/qt_impl/__init__.py
notus/win10/__init__.py
notus/win10/win10_toaster.py
Notus-0.0.3.dist-info/LICENSE.md
Notus-0.0.3.dist-info/METADATA
Notus-0.0.3.dist-info/WHEEL
Notus-0.0.3.dist-info/entry_points.txt
Notus-0.0.3.dist-info/top_level.txt
Notus-0.0.3.dist-info/RECORD
